{
  "generator-jhipster": {
    "promptValues": {
      "packageName": "com.skcc.gateway",
      "nativeLanguage": "ko",
      "microservicePath": "/Users/juyounglee/rental"
    },
    "jhipsterVersion": "6.8.0",
    "applicationType": "gateway",
    "baseName": "gateway",
    "packageName": "com.skcc.gateway",
    "packageFolder": "com/skcc/gateway",
    "serverPort": "8080",
    "authenticationType": "jwt",
    "cacheProvider": "hazelcast",
    "enableHibernateCache": true,
    "websocket": false,
    "databaseType": "sql",
    "devDatabaseType": "h2Memory",
    "prodDatabaseType": "mariadb",
    "searchEngine": false,
    "messageBroker": "kafka",
    "serviceDiscoveryType": "eureka",
    "buildTool": "maven",
    "enableSwaggerCodegen": false,
    "jwtSecretKey": "ZGI0MmIyODA5NDBiM2Y0MDNjMDAwNGRiZTQ5NGY4YTNjNmY0M2Y4M2IwYzVkMDM3N2QwZDJiNGVmMmFhZjgzOWJhNzNhYTM5NTAzMTJkMTBjYzI0MGZkYzkyMTU4YzI4YzIwMDA3NmExMGY5MDIzMjRlM2FlMGE3N2MwZDllMDg=",
    "embeddableLaunchScript": false,
    "useSass": true,
    "clientPackageManager": "npm",
    "clientFramework": "react",
    "clientTheme": "journal",
    "clientThemeVariant": "primary",
    "creationTimestamp": 1589788615709,
    "testFrameworks": ["protractor"],
    "jhiPrefix": "jhi",
    "entitySuffix": "",
    "dtoSuffix": "DTO",
    "otherModules": [],
    "enableTranslation": true,
    "nativeLanguage": "ko",
    "languages": ["ko", "en"],
    "blueprints": []
  }
}
